nullfox/__init__.py
nullfox/encrypt.py
nullfox/loader.py
nullfox/main.py
nullfox/utils.py
nullfox-0.4.0.dist-info/licenses/LICENCE
nullfox-0.4.0.dist-info/METADATA
nullfox-0.4.0.dist-info/WHEEL
nullfox-0.4.0.dist-info/top_level.txt
nullfox-0.4.0.dist-info/RECORD
