Metadata-Version: 2.4
Name: nullfox
Version: 0.4.0
Summary: A Python toolkit for encrypting and loading Lua scripts (XOR & Base64 engine)
Author-email: NullFox <pr0zone.gmaing.z@gmail.com>
License: MIT
Project-URL: Homepage, https://github.com/JojoModz/nullfox
Project-URL: Documentation, https://github.com/JojoModz/nullfox#readme
Project-URL: Source, https://github.com/JojoModz/nullfox
Project-URL: Issues, https://github.com/JojoModz/nullfox/issues
Classifier: Programming Language :: Python :: 3
Classifier: Programming Language :: Python :: 3 :: Only
Classifier: License :: OSI Approved :: MIT License
Classifier: Operating System :: OS Independent
Classifier: Topic :: Security :: Cryptography
Classifier: Topic :: Software Development :: Libraries
Requires-Python: >=3.7
License-File: LICENCE
Dynamic: license-file
